{
  "created_at": "2026-05-16T12:51:20.476931+00:00",
  "source_manifest": "outputs/audit/data_manifest.json",
  "processed_npz_exists": true,
  "raw_file_profiles": [
    {
      "path": "data/raw/real_ais_noaa_2024.csv",
      "record_count": 7295616,
      "unique_mmsi_count": 15130,
      "timestamp_min": "2024-01-02T00:00:00",
      "timestamp_max": "2024-01-02T23:59:59"
    }
  ],
  "split_counts": {
    "train": 43216,
    "val": 9260,
    "test": 9262
  },
  "coordinate_units": "degrees_latlon_wgs84",
  "metric_distance": "haversine_meters",
  "inferred_position_units": {
    "inferred": "degrees_latlon_wgs84",
    "lat_min": 13.44598,
    "lat_max": 49.5211,
    "lon_min": -158.11991,
    "lon_max": 144.63076,
    "finite_ratio": 1.0
  },
  "warnings": [],
  "metadata_limitations": [
    "The processed NPZ does not include MMSI, timestamp, vessel type, or region fields.",
    "Group-level analysis is limited to all-sample summaries unless a richer manifest is regenerated."
  ]
}